cosmic_pipeline_drf/__init__.py
cosmic_pipeline_drf/admin.py
cosmic_pipeline_drf/apps.py
cosmic_pipeline_drf/handler.py
cosmic_pipeline_drf/routers.py
cosmic_pipeline_drf/serializers.py
cosmic_pipeline_drf/tests.py
cosmic_pipeline_drf/urls.py
cosmic_pipeline_drf/views.py
cosmic_pipeline_drf-0.2.dist-info/METADATA
cosmic_pipeline_drf-0.2.dist-info/WHEEL
cosmic_pipeline_drf-0.2.dist-info/top_level.txt
cosmic_pipeline_drf-0.2.dist-info/RECORD
